sherlock/__init__.py
sherlock/__main__.py
sherlock/notify.py
sherlock/resources/data.json
sherlock/result.py
sherlock/sherlock.py
sherlock/sites.py
sherlock/tests/__init__.py
sherlock/tests/all.py
sherlock/tests/base.py
sherlock/tests/test_multiple_usernames.py
sherlockpack-0.6.0.dist-info/LICENSE
sherlockpack-0.6.0.dist-info/METADATA
sherlockpack-0.6.0.dist-info/WHEEL
sherlockpack-0.6.0.dist-info/RECORD
