Metadata-Version: 2.1
Name: sherlockpack
Version: 0.6.0
Summary: Pip package for repository github.com/sherlock-project/sherlock
Home-page: https://github.com/sherlock-project/sherlock
License: MIT
Author: Siddharth Dushantha
Maintainer: Viet Nguyen
Maintainer-email: viet@qadojo.tech
Requires-Python: >=3.11,<4.0
Classifier: License :: OSI Approved :: MIT License
Classifier: Programming Language :: Python :: 3
Classifier: Programming Language :: Python :: 3.11
Requires-Dist: certifi (>=2019.6.16)
Requires-Dist: colorama (>=0.4.1)
Requires-Dist: exrex (>=0.11.0)
Requires-Dist: openpyxl (<=3.0.10)
Requires-Dist: pandas (>=1.0.0)
Requires-Dist: pysocks (>=1.7.0)
Requires-Dist: requests (>=2.22.0)
Requires-Dist: requests-futures (>=1.0.0)
Requires-Dist: stem (>=1.8.0)
Requires-Dist: torrequest (>=0.1.0)
Project-URL: Repository, https://github.com/sherlock-project/sherlock
